HISTORY.md
LICENSE
MANIFEST.in
NOTICE
README.md
pyproject.toml
requirements-dev.txt
setup.cfg
setup.py
shortnet/__init__.py
shortnet/__version__.py
shortnet/_internal_utils.py
shortnet/adapters.py
shortnet/api.py
shortnet/auth.py
shortnet/certs.py
shortnet/compat.py
shortnet/cookies.py
shortnet/exceptions.py
shortnet/help.py
shortnet/hooks.py
shortnet/models.py
shortnet/packages.py
shortnet/sessions.py
shortnet/status_codes.py
shortnet/structures.py
shortnet/utils.py
shortnet.egg-info/PKG-INFO
shortnet.egg-info/SOURCES.txt
shortnet.egg-info/dependency_links.txt
shortnet.egg-info/not-zip-safe
shortnet.egg-info/requires.txt
shortnet.egg-info/top_level.txt
tests/__init__.py
tests/compat.py
tests/conftest.py
tests/test_help.py
tests/test_hooks.py
tests/test_lowlevel.py
tests/test_packages.py
tests/test_requests.py
tests/test_structures.py
tests/test_testserver.py
tests/test_utils.py
tests/utils.py
tests/testserver/__init__.py
tests/testserver/server.py